siyuanhelper/__init__.py
siyuanhelper/api.py
siyuanhelper/exceptions.py
siyuanhelper-0.3.0.dist-info/LICENSE
siyuanhelper-0.3.0.dist-info/WHEEL
siyuanhelper-0.3.0.dist-info/METADATA
siyuanhelper-0.3.0.dist-info/RECORD
