Metadata-Version: 2.1
Name: siyuanhelper
Version: 0.3.0
Summary: Helper lib for Siyuan Note
Home-page: https://www.github.com/Clouder0/siyuanhelper
License: MIT
Author: clouder
Author-email: clouder0@outlook.com
Requires-Python: >=3.8,<4.0
Classifier: Development Status :: 2 - Pre-Alpha
Classifier: Framework :: Flake8
Classifier: Framework :: Pytest
Classifier: Framework :: tox
Classifier: License :: OSI Approved :: MIT License
Classifier: Natural Language :: English
Classifier: Operating System :: OS Independent
Classifier: Programming Language :: Python :: 3
Classifier: Programming Language :: Python :: 3.8
Classifier: Programming Language :: Python :: 3.9
Classifier: Programming Language :: Python :: 3.10
Classifier: Programming Language :: Python :: 3.10
Classifier: Programming Language :: Python :: 3.8
Classifier: Programming Language :: Python :: 3.9
Classifier: Topic :: Utilities
Classifier: Typing :: Typed
Requires-Dist: aiohttp (>=3.8.1,<4.0.0)
Requires-Dist: asyncstdlib (>=3.10.4,<4.0.0)
Requires-Dist: cchardet (>=2.1.7,<3.0.0)
Project-URL: Documentation, https://clouder0.github.io/siyuanhelper
Project-URL: Repository, https://www.github.com/Clouder0/siyuanhelper
